.gitignore
CONTRIBUTORS.txt
MANIFEST.in
README.rst
bootstrap.py
buildout.cfg
setup.py
collective/__init__.py
collective.plonefinder.egg-info/PKG-INFO
collective.plonefinder.egg-info/SOURCES.txt
collective.plonefinder.egg-info/dependency_links.txt
collective.plonefinder.egg-info/entry_points.txt
collective.plonefinder.egg-info/namespace_packages.txt
collective.plonefinder.egg-info/not-zip-safe
collective.plonefinder.egg-info/requires.txt
collective.plonefinder.egg-info/top_level.txt
collective/plonefinder/__init__.py
collective/plonefinder/config.py
collective/plonefinder/configure.zcml
collective/plonefinder/utils.py
collective/plonefinder/browser/__init__.py
collective/plonefinder/browser/configure.zcml
collective/plonefinder/browser/finder.pt
collective/plonefinder/browser/finder.py
collective/plonefinder/browser/finder_batch.pt
collective/plonefinder/browser/finder_newfolder.pt
collective/plonefinder/browser/finder_newfolder.py
collective/plonefinder/browser/interfaces.py
collective/plonefinder/browser/ticket.py
collective/plonefinder/browser/typescss.py
collective/plonefinder/browser/uploadcapable.py
collective/plonefinder/browser/dtml/content-types.css.dtml
collective/plonefinder/browser/elm/.gitignore
collective/plonefinder/browser/elm/build.sh
collective/plonefinder/browser/elm/elm-package.json
collective/plonefinder/browser/elm/imagewidget.elm
collective/plonefinder/browser/static/action_menu_button_bg.png
collective/plonefinder/browser/static/action_menu_button_selected_bg.png
collective/plonefinder/browser/static/browsable-content.png
collective/plonefinder/browser/static/browser_newfolder.png
collective/plonefinder/browser/static/browser_pres_files.png
collective/plonefinder/browser/static/browser_pres_images.png
collective/plonefinder/browser/static/browser_upload.png
collective/plonefinder/browser/static/cancel.png
collective/plonefinder/browser/static/circle_animation.gif
collective/plonefinder/browser/static/close_icon.gif
collective/plonefinder/browser/static/contenttypes-sprite.png
collective/plonefinder/browser/static/finder-iefixes.css
collective/plonefinder/browser/static/finder.css
collective/plonefinder/browser/static/finder.js
collective/plonefinder/browser/static/folder_explore.png
collective/plonefinder/browser/static/folder_image.png
collective/plonefinder/browser/static/folder_up.png
