Metadata-Version: 1.1
Name: collective.plonefinder
Version: 1.3.1
Summary: A finder to search/select portal objects for Plone
Home-page: http://www.alterway.fr
Author: Jean-mat Grimaldi / Alter Way Solutions
Author-email: support@ingeniweb.com
License: GPL
Keywords: Zope Plone Medias Finder
Platform: UNKNOWN
Classifier: Environment :: Web Environment
Classifier: License :: OSI Approved :: GNU General Public License (GPL)
Classifier: Operating System :: OS Independent
Classifier: Framework :: Zope2
Classifier: Framework :: Plone
Classifier: Framework :: Plone :: 4.0
Classifier: Framework :: Plone :: 4.1
Classifier: Framework :: Plone :: 4.2
Classifier: Framework :: Plone :: 4.3
Classifier: Intended Audience :: Developers
Classifier: Programming Language :: Python
Classifier: Programming Language :: Python :: 2.6
Classifier: Programming Language :: Python :: 2.7
Classifier: Topic :: Software Development :: Libraries :: Python Modules
